dyncfg/__init__.py
dyncfg/config_value.py
dyncfg/config_value_list.py
dyncfg/config_value_list.pyi
dyncfg/dynamic_config.py
dyncfg/py.typed
dyncfg/section.py
dyncfg-0.5.2.dist-info/licenses/LICENSE
dyncfg-0.5.2.dist-info/METADATA
dyncfg-0.5.2.dist-info/WHEEL
dyncfg-0.5.2.dist-info/top_level.txt
dyncfg-0.5.2.dist-info/RECORD
