Metadata-Version: 2.4
Name: dyncfg
Version: 0.5.2
Summary: A dynamic, easy-to-use .ini configuration system built for humans.
Home-page: https://github.com/lukasgolson/dyncfg
Author: Lukas G. Olson
Author-email: olson@student.ubc.ca
Classifier: Programming Language :: Python :: 3
Classifier: License :: OSI Approved :: MIT License
Classifier: Operating System :: OS Independent
Requires-Python: >=3.6
License-File: LICENSE
Provides-Extra: pandas
Requires-Dist: pandas; extra == "pandas"
Dynamic: author
Dynamic: author-email
Dynamic: classifier
Dynamic: description
Dynamic: description-content-type
Dynamic: home-page
Dynamic: license-file
Dynamic: provides-extra
Dynamic: requires-python
Dynamic: summary
